{
  "id": "4031918",
  "name": "no name",
  "font_family": "iconfont",
  "css_prefix_text": "icon-",
  "description": "",
  "glyphs": [
    {
      "icon_id": "21242869",
      "name": "分类",
      "font_class": "fenlei",
      "unicode": "e63a",
      "unicode_decimal": 58938
    },
    {
      "icon_id": "705684",
      "name": "日历",
      "font_class": "rili",
      "unicode": "e620",
      "unicode_decimal": 58912
    },
    {
      "icon_id": "4933250",
      "name": "更新时间",
      "font_class": "gengxinshijian",
      "unicode": "e705",
      "unicode_decimal": 59141
    },
    {
      "icon_id": "4447925",
      "name": "评论",
      "font_class": "pinglun",
      "unicode": "e66b",
      "unicode_decimal": 58987
    },
    {
      "icon_id": "11398968",
      "name": "grip-vertical",
      "font_class": "grip-vertical",
      "unicode": "e600",
      "unicode_decimal": 58880
    },
    {
      "icon_id": "1719343",
      "name": "随机",
      "font_class": "suiji",
      "unicode": "e7b8",
      "unicode_decimal": 59320
    },
    {
      "icon_id": "2377197",
      "name": "夜间模式",
      "font_class": "yejianmoshi",
      "unicode": "e6c1",
      "unicode_decimal": 59073
    },
    {
      "icon_id": "4572509",
      "name": "搜索",
      "font_class": "sousuo",
      "unicode": "e60c",
      "unicode_decimal": 58892
    },
    {
      "icon_id": "12578858",
      "name": "home",
      "font_class": "home",
      "unicode": "e6bc",
      "unicode_decimal": 59068
    }
  ]
}
